odoo/addons/pos_partner_birthdate/README.rst
odoo/addons/pos_partner_birthdate/__init__.py
odoo/addons/pos_partner_birthdate/__manifest__.py
odoo/addons/pos_partner_birthdate/i18n/pos_partner_birthdate.pot
odoo/addons/pos_partner_birthdate/readme/CONTRIBUTORS.rst
odoo/addons/pos_partner_birthdate/readme/DESCRIPTION.rst
odoo/addons/pos_partner_birthdate/static/description/icon.png
odoo/addons/pos_partner_birthdate/static/description/index.html
odoo/addons/pos_partner_birthdate/static/src/js/models.js
odoo/addons/pos_partner_birthdate/static/src/xml/ClientDetailsEdit.xml
odoo/addons/pos_partner_birthdate/views/assets.xml
odoo14_addon_pos_partner_birthdate-14.0.1.0.2.dist-info/METADATA
odoo14_addon_pos_partner_birthdate-14.0.1.0.2.dist-info/WHEEL
odoo14_addon_pos_partner_birthdate-14.0.1.0.2.dist-info/top_level.txt
odoo14_addon_pos_partner_birthdate-14.0.1.0.2.dist-info/RECORD
